spa/__init__.py
spa/middleware.py
spa/storage.py
tests/__init__.py
tests/test_spa.py
django_spa-0.3.6.dist-info/AUTHORS.rst
django_spa-0.3.6.dist-info/LICENSE
django_spa-0.3.6.dist-info/METADATA
django_spa-0.3.6.dist-info/WHEEL
django_spa-0.3.6.dist-info/top_level.txt
django_spa-0.3.6.dist-info/RECORD
