Metadata-Version: 1.1
Name: django-spa
Version: 0.3.6
Summary: Simple Django configuration to serve a single-page app
Home-page: https://github.com/metakermit/django-spa
Author: Dražen Lučanin
Author-email: kermit666@gmail.com
License: MIT license
Keywords: django spa django-spa react angular yeoman heroku
Platform: UNKNOWN
Classifier: Development Status :: 2 - Pre-Alpha
Classifier: Intended Audience :: Developers
Classifier: License :: OSI Approved :: MIT License
Classifier: Natural Language :: English
Classifier: Programming Language :: Python :: 3
Classifier: Programming Language :: Python :: 3.6
Classifier: Programming Language :: Python :: 3.7
Classifier: Framework :: Django
